fm/__init__.py
fm/__version__.py
fm/cli.py
fm/main.py
fm/commands/__init__.py
fm/commands/bump.py
fm/commands/graph.py
fm/commands/hooks.py
fm/commands/init.py
fm/commands/list.py
fm/commands/tag.py
fm/commands/tree.py
fm/commands/validate.py
fm/commands/whoami.py
fm/utils/__init__.py
fm/utils/io.py
fm/utils/model.py
fm/utils/scanner.py
fm/utils/validator.py
folder_metadata-0.1.0.dist-info/licenses/LICENSE
folder_metadata-0.1.0.dist-info/METADATA
folder_metadata-0.1.0.dist-info/WHEEL
folder_metadata-0.1.0.dist-info/entry_points.txt
folder_metadata-0.1.0.dist-info/top_level.txt
folder_metadata-0.1.0.dist-info/RECORD
