Metadata-Version: 2.4
Name: folder-metadata
Version: 0.1.0
Summary: CLI tool for managing structured metadata in monorepos and multi-project repositories
Author-email: Peter Corcoran <pmcorcor@gmail.com>
License: MIT License
Project-URL: Homepage, https://github.com/corcoranp/folder-metadata
Project-URL: Repository, https://github.com/corcoranp/folder-metadata
Project-URL: Issues, https://github.com/corcoranp/folder-metadata/issues
Project-URL: Documentation, https://github.com/corcoranp/folder-metadata#readme
Keywords: cli,monorepo,metadata,project-management,tooling
Classifier: Development Status :: 4 - Beta
Classifier: Environment :: Console
Classifier: Intended Audience :: Developers
Classifier: License :: OSI Approved :: MIT License
Classifier: Operating System :: OS Independent
Classifier: Programming Language :: Python :: 3
Classifier: Programming Language :: Python :: 3.8
Classifier: Programming Language :: Python :: 3.9
Classifier: Programming Language :: Python :: 3.10
Classifier: Programming Language :: Python :: 3.11
Classifier: Programming Language :: Python :: 3.12
Classifier: Topic :: Software Development :: Libraries :: Python Modules
Classifier: Topic :: System :: Systems Administration
Classifier: Topic :: Utilities
Requires-Python: >=3.8
License-File: LICENSE
Requires-Dist: typer[all]>=0.9.0
Requires-Dist: rich>=13.0.0
Requires-Dist: pydantic>=2.0.0
Requires-Dist: semver>=3.0.0
Requires-Dist: PyYAML>=6.0
Provides-Extra: dev
Requires-Dist: pytest>=7.0.0; extra == "dev"
Requires-Dist: pytest-cov>=4.0.0; extra == "dev"
Requires-Dist: black>=23.0.0; extra == "dev"
Requires-Dist: flake8>=6.0.0; extra == "dev"
Requires-Dist: mypy>=1.0.0; extra == "dev"
Requires-Dist: pre-commit>=3.0.0; extra == "dev"
Requires-Dist: types-PyYAML; extra == "dev"
Provides-Extra: test
Requires-Dist: pytest>=7.0.0; extra == "test"
Requires-Dist: pytest-cov>=4.0.0; extra == "test"
Requires-Dist: pytest-mock>=3.10.0; extra == "test"
Dynamic: license-file
